coderfastapi/__init__.py
coderfastapi/test.py
coderfastapi/handlers/__init__.py
coderfastapi/handlers/version.py
coderfastapi/lib/__init__.py
coderfastapi/lib/router.py
coderfastapi/lib/signature.py
coderfastapi/lib/decorators/__init__.py
coderfastapi/lib/decorators/pagination.py
coderfastapi/lib/decorators/util.py
coderfastapi/lib/security/__init__.py
coderfastapi/lib/security/acl.py
coderfastapi/lib/security/policies/__init__.py
coderfastapi/lib/security/policies/authentication/__init__.py
coderfastapi/lib/security/policies/authentication/session.py
coderfastapi/lib/security/policies/authentication/jwt/__init__.py
coderfastapi/lib/security/policies/authentication/jwt/providers/__init__.py
coderfastapi/lib/security/policies/authentication/jwt/providers/expiration.py
coderfastapi/lib/security/policies/authentication/jwt/providers/recovery.py
coderfastapi/lib/security/policies/authentication/jwt/providers/user.py
coderfastapi/lib/security/policies/authorization/__init__.py
coderfastapi/lib/security/policies/authorization/user.py
coderfastapi/lib/security/session/__init__.py
coderfastapi/lib/security/session/base.py
coderfastapi/lib/security/session/user.py
coderfastapi/lib/validation/__init__.py
coderfastapi/lib/validation/schemas/__init__.py
coderfastapi/lib/validation/schemas/aggregation.py
coderfastapi/lib/validation/schemas/pagination.py
coderfastapi/lib/validation/schemas/query.py
coderfastapi/lib/validation/schemas/request.py
coderfastapi/lib/validation/schemas/version.py
coderfastapi/logging/__init__.py
coderfastapi/logging/context.py
coderfastapi/logging/filter.py
coderfastapi/logging/middleware.py
coderfastapi-6.0.0.dist-info/METADATA
coderfastapi-6.0.0.dist-info/WHEEL
coderfastapi-6.0.0.dist-info/top_level.txt
coderfastapi-6.0.0.dist-info/RECORD
