Metadata-Version: 2.4
Name: coderfastapi
Version: 6.0.0
Summary: coderfastapi
Author-email: Code R <hello@coderstudio.dev>
Requires-Dist: codercore~=8.0
Requires-Dist: fastapi[all]~=0.89
Requires-Dist: google-cloud-logging~=3.7
Requires-Dist: orjson~=3.8
Requires-Dist: pydantic~=2.4
Requires-Dist: python-jose~=3.3
Provides-Extra: test
Requires-Dist: pytest~=7.2; extra == "test"
Requires-Dist: pytest-asyncio~=0.20; extra == "test"
Requires-Dist: pytest-cov~=4.0; extra == "test"
Requires-Dist: pytest-mock~=3.10; extra == "test"
Requires-Dist: pytest-xdist[psutil]~=3.1; extra == "test"
Provides-Extra: dev
Requires-Dist: black~=22.12; extra == "dev"
Requires-Dist: bumpver~=2023.1127; extra == "dev"
Requires-Dist: flake8~=6.0; extra == "dev"
Requires-Dist: isort~=5.12; extra == "dev"
